fk_audit_flask/__init__.py
fk_audit_flask/config.py
fk_audit_flask/main.py
fk_audit_flask/audit/__init__.py
fk_audit_flask/audit/kwargs.py
fk_audit_flask/audit/mongoengine.py
fk_audit_flask/audit/sqlalchemy/__init__.py
fk_audit_flask/audit/sqlalchemy/instances.py
fk_audit_flask/audit/sqlalchemy/sqlalchemy.py
fk_audit_flask/utils/__init__.py
fk_audit_flask/utils/flask.py
fk_audit_flask/utils/json.py
test/__init__.py
test/config.py
test/test_mongoengine.py
test/test_sqlalchemy.py
fk_audit_flask-0.1.4.dist-info/METADATA
fk_audit_flask-0.1.4.dist-info/WHEEL
fk_audit_flask-0.1.4.dist-info/top_level.txt
fk_audit_flask-0.1.4.dist-info/RECORD
